nameko_redis/__init__.py
nameko_redis/client_providers.py
nameko_redis/pubsub_response_listener.py
nameko_redis_py-0.1.0.dist-info/DESCRIPTION.rst
nameko_redis_py-0.1.0.dist-info/METADATA
nameko_redis_py-0.1.0.dist-info/RECORD
nameko_redis_py-0.1.0.dist-info/WHEEL
nameko_redis_py-0.1.0.dist-info/metadata.json
nameko_redis_py-0.1.0.dist-info/top_level.txt
