Metadata-Version: 2.0
Name: nameko-redis-py
Version: 0.1.0
Summary: Redis dependency and utils for Nameko
Home-page: https://github.com/fraglab/nameko-redis-py
Author: Sergey Suglobov
Author-email: s.suglobov@gmail.com
License: UNKNOWN
Keywords: nameko,redis,redis-utils
Platform: UNKNOWN
Classifier: Environment :: Console
Classifier: Intended Audience :: Developers
Classifier: License :: OSI Approved :: MIT License
Classifier: Natural Language :: English
Classifier: Operating System :: Microsoft :: Windows
Classifier: Operating System :: POSIX
Classifier: Programming Language :: Python :: 3.6
Classifier: Programming Language :: Python :: 3.5
Classifier: Programming Language :: Python :: 3 :: Only
Requires-Dist: nameko
Requires-Dist: redis
Requires-Dist: setuptools
